srbogrid/__init__.py
srbogrid/srbo.py
srbogrid-0.2.1.dist-info/LICENSE.rst
srbogrid-0.2.1.dist-info/LICENSE.md
srbogrid-0.2.1.dist-info/WHEEL
srbogrid-0.2.1.dist-info/METADATA
srbogrid-0.2.1.dist-info/RECORD
